{
  "id": "MAP_UNION_CITY_ABANDONED_MUSEUM",
  "name": "UnionCity_AbandonedMuseum",
  "layout": "LAYOUT_UNION_CITY_ABANDONED_MUSEUM",
  "music": "MUS_ABANDONED_MUSEUM",
  "region_map_section": "MAPSEC_UNION_CITY",
  "requires_flash": false,
  "weather": "WEATHER_NONE",
  "map_type": "MAP_TYPE_INDOOR",
  "allow_cycling": false,
  "allow_escaping": false,
  "allow_running": true,
  "show_map_name": false,
  "battle_scene": "MAP_BATTLE_SCENE_NORMAL",
  "connections": 0,
  "object_events": [
    {
      "graphics_id": "OBJ_EVENT_GFX_WOMAN_3",
      "x": 11,
      "y": 32,
      "elevation": 3,
      "movement_type": "MOVEMENT_TYPE_WANDER_AROUND",
      "movement_range_x": 0,
      "movement_range_y": 0,
      "trainer_type": "TRAINER_TYPE_NONE",
      "trainer_sight_or_berry_tree_id": "0",
      "script": "UnionCity_AbandonedMuseum_Girl",
      "flag": "0"
    },
    {
      "graphics_id": "OBJ_EVENT_GFX_OLD_MAN",
      "x": 8,
      "y": 36,
      "elevation": 3,
      "movement_type": "MOVEMENT_TYPE_WANDER_AROUND",
      "movement_range_x": 0,
      "movement_range_y": 0,
      "trainer_type": "TRAINER_TYPE_NONE",
      "trainer_sight_or_berry_tree_id": "0",
      "script": "UnionCity_AbandonedMuseum_Old_Man",
      "flag": "0"
    },
    {
      "graphics_id": "OBJ_EVENT_GFX_LITTLE_GIRL",
      "x": 25,
      "y": 32,
      "elevation": 3,
      "movement_type": "MOVEMENT_TYPE_WANDER_AROUND",
      "movement_range_x": 0,
      "movement_range_y": 0,
      "trainer_type": "TRAINER_TYPE_NONE",
      "trainer_sight_or_berry_tree_id": "0",
      "script": "UnionCity_AbandonedMuseum_Little_Girl",
      "flag": "0"
    },
    {
      "graphics_id": "OBJ_EVENT_GFX_AQUA_MEMBER_M",
      "x": 12,
      "y": 16,
      "elevation": 3,
      "movement_type": "MOVEMENT_TYPE_FACE_UP",
      "movement_range_x": 0,
      "movement_range_y": 0,
      "trainer_type": "TRAINER_TYPE_RUN_SCRIPT",
      "trainer_sight_or_berry_tree_id": "3",
      "script": "UnionCity_AbandonedMuseum_Male_SUBO",
      "flag": "FLAG_HIDE_ABANDONED_MUSEUM_SUBO"
    },
    {
      "graphics_id": "OBJ_EVENT_GFX_AQUA_MEMBER_M",
      "x": 7,
      "y": 20,
      "elevation": 3,
      "movement_type": "MOVEMENT_TYPE_WALK_SEQUENCE_UP_LEFT_DOWN_RIGHT",
      "movement_range_x": 2,
      "movement_range_y": 2,
      "trainer_type": "TRAINER_TYPE_RUN_SCRIPT",
      "trainer_sight_or_berry_tree_id": "4",
      "script": "UnionCity_AbandonedMuseum_Male_SUBO",
      "flag": "FLAG_HIDE_ABANDONED_MUSEUM_SUBO"
    },
    {
      "graphics_id": "OBJ_EVENT_GFX_AQUA_MEMBER_F",
      "x": 7,
      "y": 14,
      "elevation": 3,
      "movement_type": "MOVEMENT_TYPE_FACE_DOWN_UP_AND_RIGHT",
      "movement_range_x": 0,
      "movement_range_y": 0,
      "trainer_type": "TRAINER_TYPE_RUN_SCRIPT",
      "trainer_sight_or_berry_tree_id": "4",
      "script": "UnionCity_AbandonedMuseum_Female_SUBO",
      "flag": "FLAG_HIDE_ABANDONED_MUSEUM_SUBO"
    },
    {
      "graphics_id": "OBJ_EVENT_GFX_AQUA_MEMBER_M",
      "x": 7,
      "y": 6,
      "elevation": 3,
      "movement_type": "MOVEMENT_TYPE_WALK_SEQUENCE_LEFT_UP_RIGHT_DOWN",
      "movement_range_x": 3,
      "movement_range_y": 3,
      "trainer_type": "TRAINER_TYPE_RUN_SCRIPT",
      "trainer_sight_or_berry_tree_id": "4",
      "script": "UnionCity_AbandonedMuseum_Male_SUBO",
      "flag": "FLAG_HIDE_ABANDONED_MUSEUM_SUBO"
    },
    {
      "graphics_id": "OBJ_EVENT_GFX_AQUA_MEMBER_F",
      "x": 11,
      "y": 4,
      "elevation": 3,
      "movement_type": "MOVEMENT_TYPE_WALK_SEQUENCE_LEFT_DOWN_RIGHT_UP",
      "movement_range_x": 3,
      "movement_range_y": 3,
      "trainer_type": "TRAINER_TYPE_RUN_SCRIPT",
      "trainer_sight_or_berry_tree_id": "4",
      "script": "UnionCity_AbandonedMuseum_Female_SUBO",
      "flag": "FLAG_HIDE_ABANDONED_MUSEUM_SUBO"
    },
    {
      "graphics_id": "OBJ_EVENT_GFX_AQUA_MEMBER_F",
      "x": 24,
      "y": 7,
      "elevation": 3,
      "movement_type": "MOVEMENT_TYPE_NONE",
      "movement_range_x": 0,
      "movement_range_y": 0,
      "trainer_type": "TRAINER_TYPE_RUN_SCRIPT",
      "trainer_sight_or_berry_tree_id": "1",
      "script": "UnionCity_AbandonedMuseum_Female_SUBO",
      "flag": "FLAG_HIDE_ABANDONED_MUSEUM_SUBO"
    },
    {
      "graphics_id": "OBJ_EVENT_GFX_AQUA_MEMBER_F",
      "x": 31,
      "y": 5,
      "elevation": 3,
      "movement_type": "MOVEMENT_TYPE_FACE_UP",
      "movement_range_x": 0,
      "movement_range_y": 0,
      "trainer_type": "TRAINER_TYPE_RUN_SCRIPT",
      "trainer_sight_or_berry_tree_id": "3",
      "script": "UnionCity_AbandonedMuseum_Female_SUBO",
      "flag": "FLAG_HIDE_ABANDONED_MUSEUM_SUBO"
    },
    {
      "graphics_id": "OBJ_EVENT_GFX_AQUA_MEMBER_F",
      "x": 32,
      "y": 16,
      "elevation": 3,
      "movement_type": "MOVEMENT_TYPE_FACE_RIGHT",
      "movement_range_x": 0,
      "movement_range_y": 0,
      "trainer_type": "TRAINER_TYPE_NONE",
      "trainer_sight_or_berry_tree_id": "0",
      "script": "NULL",
      "flag": "FLAG_HIDE_ABANDONED_MUSEUM_SUBO"
    },
    {
      "graphics_id": "OBJ_EVENT_GFX_ARCHIE",
      "x": 31,
      "y": 17,
      "elevation": 3,
      "movement_type": "MOVEMENT_TYPE_FACE_RIGHT",
      "movement_range_x": 0,
      "movement_range_y": 0,
      "trainer_type": "TRAINER_TYPE_NONE",
      "trainer_sight_or_berry_tree_id": "0",
      "script": "NULL",
      "flag": "FLAG_HIDE_ABANDONED_MUSEUM_SUBO"
    },
    {
      "graphics_id": "OBJ_EVENT_GFX_AQUA_MEMBER_M",
      "x": 32,
      "y": 18,
      "elevation": 3,
      "movement_type": "MOVEMENT_TYPE_FACE_RIGHT",
      "movement_range_x": 0,
      "movement_range_y": 0,
      "trainer_type": "TRAINER_TYPE_NONE",
      "trainer_sight_or_berry_tree_id": "0",
      "script": "NULL",
      "flag": "FLAG_HIDE_ABANDONED_MUSEUM_SUBO"
    },
    {
      "graphics_id": "OBJ_EVENT_GFX_SCHOOL_KID_M",
      "x": 33,
      "y": 17,
      "elevation": 3,
      "movement_type": "MOVEMENT_TYPE_FACE_LEFT",
      "movement_range_x": 0,
      "movement_range_y": 0,
      "trainer_type": "TRAINER_TYPE_NONE",
      "trainer_sight_or_berry_tree_id": "0",
      "script": "NULL",
      "flag": "FLAG_HIDE_ABANDONED_MUSEUM_SUBO"
    },
    {
      "graphics_id": "OBJ_EVENT_GFX_MAGMA_MEMBER_M",
      "x": 33,
      "y": 17,
      "elevation": 3,
      "movement_type": "MOVEMENT_TYPE_FACE_LEFT",
      "movement_range_x": 0,
      "movement_range_y": 0,
      "trainer_type": "TRAINER_TYPE_NONE",
      "trainer_sight_or_berry_tree_id": "0",
      "script": "NULL",
      "flag": "FLAG_HIDE_ABANDONED_MUSEUM_SUBO"
    },
    {
      "graphics_id": "OBJ_EVENT_GFX_RATTATA",
      "x": 32,
      "y": 17,
      "elevation": 3,
      "movement_type": "MOVEMENT_TYPE_NONE",
      "movement_range_x": 0,
      "movement_range_y": 0,
      "trainer_type": "TRAINER_TYPE_NONE",
      "trainer_sight_or_berry_tree_id": "0",
      "script": "NULL",
      "flag": "FLAG_HIDE_ABANDONED_MUSEUM_SUBO"
    },
    {
      "graphics_id": "OBJ_EVENT_GFX_ITEM_BALL",
      "x": 32,
      "y": 17,
      "elevation": 3,
      "movement_type": "MOVEMENT_TYPE_NONE",
      "movement_range_x": 0,
      "movement_range_y": 0,
      "trainer_type": "TRAINER_TYPE_NONE",
      "trainer_sight_or_berry_tree_id": "0",
      "script": "NULL",
      "flag": "FLAG_HIDE_ABANDONED_MUSEUM_POKE_BALL"
    },
    {
      "graphics_id": "OBJ_EVENT_GFX_AQUA_MEMBER_M",
      "x": 18,
      "y": 8,
      "elevation": 3,
      "movement_type": "MOVEMENT_TYPE_WALK_SEQUENCE_UP_LEFT_DOWN_RIGHT",
      "movement_range_x": 5,
      "movement_range_y": 5,
      "trainer_type": "TRAINER_TYPE_RUN_SCRIPT",
      "trainer_sight_or_berry_tree_id": "4",
      "script": "UnionCity_AbandonedMuseum_Male_SUBO",
      "flag": "FLAG_HIDE_ABANDONED_MUSEUM_SUBO"
    }
  ],
  "warp_events": [
    {
      "x": 18,
      "y": 39,
      "elevation": 3,
      "dest_map": "MAP_UNION_CITY",
      "dest_warp_id": "11"
    },
    {
      "x": 17,
      "y": 39,
      "elevation": 3,
      "dest_map": "MAP_UNION_CITY",
      "dest_warp_id": "11"
    },
    {
      "x": 15,
      "y": 12,
      "elevation": 3,
      "dest_map": "MAP_MUDDY_UNDERPASS",
      "dest_warp_id": "0"
    }
  ],
  "coord_events": [
    {
      "type": "trigger",
      "x": 33,
      "y": 11,
      "elevation": 0,
      "var": "VAR_STORYLINE_STATE",
      "var_value": "13",
      "script": "UnionCity_SUBO_Event"
    },
    {
      "type": "trigger",
      "x": 34,
      "y": 11,
      "elevation": 0,
      "var": "VAR_STORYLINE_STATE",
      "var_value": "13",
      "script": "UnionCity_SUBO_Event"
    }
  ],
  "bg_events": [
    {
      "type": "sign",
      "x": 3,
      "y": 35,
      "elevation": 0,
      "player_facing_dir": "BG_EVENT_PLAYER_FACING_ANY",
      "script": "UnionCity_AbandonedMuseum_DragonitesWeatheredMailBag"
    },
    {
      "type": "sign",
      "x": 3,
      "y": 38,
      "elevation": 0,
      "player_facing_dir": "BG_EVENT_PLAYER_FACING_ANY",
      "script": "UnionCity_AbandonedMuseum_AncientGengarShadowRelic"
    },
    {
      "type": "sign",
      "x": 25,
      "y": 35,
      "elevation": 0,
      "player_facing_dir": "BG_EVENT_PLAYER_FACING_ANY",
      "script": "UnionCity_AbandonedMuseum_AncientSpindaPatternedPottery"
    },
    {
      "type": "sign",
      "x": 26,
      "y": 35,
      "elevation": 0,
      "player_facing_dir": "BG_EVENT_PLAYER_FACING_ANY",
      "script": "UnionCity_AbandonedMuseum_AncientSpindaPatternedPottery"
    },
    {
      "type": "sign",
      "x": 30,
      "y": 35,
      "elevation": 0,
      "player_facing_dir": "BG_EVENT_PLAYER_FACING_ANY",
      "script": "UnionCity_AbandonedMuseum_LatiasLatiosTwinFeathers"
    },
    {
      "type": "sign",
      "x": 30,
      "y": 38,
      "elevation": 0,
      "player_facing_dir": "BG_EVENT_PLAYER_FACING_ANY",
      "script": "UnionCity_AbandonedMuseum_GoldenMagikarpScales"
    },
    {
      "type": "sign",
      "x": 34,
      "y": 35,
      "elevation": 0,
      "player_facing_dir": "BG_EVENT_PLAYER_FACING_ANY",
      "script": "UnionCity_AbandonedMuseum_PikachusElectricRod"
    },
    {
      "type": "sign",
      "x": 34,
      "y": 38,
      "elevation": 0,
      "player_facing_dir": "BG_EVENT_PLAYER_FACING_ANY",
      "script": "UnionCity_AbandonedMuseum_AncientPokeBallShard"
    },
    {
      "type": "sign",
      "x": 14,
      "y": 16,
      "elevation": 0,
      "player_facing_dir": "BG_EVENT_PLAYER_FACING_ANY",
      "script": "UnionCity_AbandonedMuseum_AncientIcyRockRegice"
    },
    {
      "type": "sign",
      "x": 10,
      "y": 16,
      "elevation": 0,
      "player_facing_dir": "BG_EVENT_PLAYER_FACING_ANY",
      "script": "UnionCity_AbandonedMuseum_AncientUnownTablet"
    },
    {
      "type": "sign",
      "x": 14,
      "y": 19,
      "elevation": 0,
      "player_facing_dir": "BG_EVENT_PLAYER_FACING_ANY",
      "script": "UnionCity_AbandonedMuseum_AncientSkyPillarScroll"
    },
    {
      "type": "sign",
      "x": 12,
      "y": 19,
      "elevation": 0,
      "player_facing_dir": "BG_EVENT_PLAYER_FACING_ANY",
      "script": "UnionCity_AbandonedMuseum_AncientArmaldoFossilizedClaw"
    },
    {
      "type": "sign",
      "x": 8,
      "y": 19,
      "elevation": 0,
      "player_facing_dir": "BG_EVENT_PLAYER_FACING_ANY",
      "script": "UnionCity_AbandonedMuseum_FossilizedLileepBlossom"
    },
    {
      "type": "sign",
      "x": 6,
      "y": 16,
      "elevation": 0,
      "player_facing_dir": "BG_EVENT_PLAYER_FACING_ANY",
      "script": "UnionCity_AbandonedMuseum_RegirocksEnigmaticKeystone"
    },
    {
      "type": "sign",
      "x": 6,
      "y": 19,
      "elevation": 0,
      "player_facing_dir": "BG_EVENT_PLAYER_FACING_ANY",
      "script": "UnionCity_AbandonedMuseum_EeveeEvolutionStones"
    },
    {
      "type": "sign",
      "x": 6,
      "y": 5,
      "elevation": 0,
      "player_facing_dir": "BG_EVENT_PLAYER_FACING_ANY",
      "script": "UnionCity_AbandonedMuseum_AncientOmanyteShell"
    },
    {
      "type": "sign",
      "x": 10,
      "y": 6,
      "elevation": 0,
      "player_facing_dir": "BG_EVENT_PLAYER_FACING_ANY",
      "script": "UnionCity_AbandonedMuseum_KabutoFossil"
    },
    {
      "type": "sign",
      "x": 12,
      "y": 5,
      "elevation": 0,
      "player_facing_dir": "BG_EVENT_PLAYER_FACING_ANY",
      "script": "UnionCity_AbandonedMuseum_MetagrossCoreCrystal"
    },
    {
      "type": "sign",
      "x": 24,
      "y": 6,
      "elevation": 0,
      "player_facing_dir": "BG_EVENT_PLAYER_FACING_ANY",
      "script": "UnionCity_AbandonedMuseum_ReconstructedAerodactylExhibit"
    },
    {
      "type": "sign",
      "x": 29,
      "y": 5,
      "elevation": 0,
      "player_facing_dir": "BG_EVENT_PLAYER_FACING_ANY",
      "script": "UnionCity_AbandonedMuseum_AncientUnownTablet"
    },
    {
      "type": "sign",
      "x": 30,
      "y": 5,
      "elevation": 0,
      "player_facing_dir": "BG_EVENT_PLAYER_FACING_ANY",
      "script": "UnionCity_AbandonedMuseum_AncientUnownTablet"
    },
    {
      "type": "sign",
      "x": 32,
      "y": 5,
      "elevation": 0,
      "player_facing_dir": "BG_EVENT_PLAYER_FACING_ANY",
      "script": "UnionCity_AbandonedMuseum_AncientSpindaPatternedPottery"
    },
    {
      "type": "sign",
      "x": 33,
      "y": 5,
      "elevation": 0,
      "player_facing_dir": "BG_EVENT_PLAYER_FACING_ANY",
      "script": "UnionCity_AbandonedMuseum_AncientSpindaPatternedPottery"
    },
    {
      "type": "sign",
      "x": 7,
      "y": 1,
      "elevation": 0,
      "player_facing_dir": "BG_EVENT_PLAYER_FACING_ANY",
      "script": "UnionCity_AbandonedMuseum_RelicanthFossil"
    },
    {
      "type": "sign",
      "x": 8,
      "y": 1,
      "elevation": 0,
      "player_facing_dir": "BG_EVENT_PLAYER_FACING_ANY",
      "script": "UnionCity_AbandonedMuseum_RelicanthFossil"
    },
    {
      "type": "sign",
      "x": 31,
      "y": 1,
      "elevation": 0,
      "player_facing_dir": "BG_EVENT_PLAYER_FACING_ANY",
      "script": "UnionCity_AbandonedMuseum_RelicanthFossil"
    },
    {
      "type": "sign",
      "x": 32,
      "y": 1,
      "elevation": 0,
      "player_facing_dir": "BG_EVENT_PLAYER_FACING_ANY",
      "script": "UnionCity_AbandonedMuseum_RelicanthFossil"
    },
    {
      "type": "sign",
      "x": 29,
      "y": 12,
      "elevation": 0,
      "player_facing_dir": "BG_EVENT_PLAYER_FACING_ANY",
      "script": "UnionCity_AbandonedMuseum_RelicanthFossil"
    },
    {
      "type": "sign",
      "x": 30,
      "y": 12,
      "elevation": 0,
      "player_facing_dir": "BG_EVENT_PLAYER_FACING_ANY",
      "script": "UnionCity_AbandonedMuseum_RelicanthFossil"
    },
    {
      "type": "sign",
      "x": 26,
      "y": 15,
      "elevation": 0,
      "player_facing_dir": "BG_EVENT_PLAYER_FACING_ANY",
      "script": "UnionCity_AbandonedMuseum_AncientSpindaPatternedPottery"
    },
    {
      "type": "sign",
      "x": 27,
      "y": 15,
      "elevation": 0,
      "player_facing_dir": "BG_EVENT_PLAYER_FACING_ANY",
      "script": "UnionCity_AbandonedMuseum_AncientSpindaPatternedPottery"
    },
    {
      "type": "sign",
      "x": 26,
      "y": 19,
      "elevation": 0,
      "player_facing_dir": "BG_EVENT_PLAYER_FACING_ANY",
      "script": "UnionCity_AbandonedMuseum_AncientSpindaPatternedPottery"
    },
    {
      "type": "sign",
      "x": 27,
      "y": 19,
      "elevation": 0,
      "player_facing_dir": "BG_EVENT_PLAYER_FACING_ANY",
      "script": "UnionCity_AbandonedMuseum_AncientSpindaPatternedPottery"
    },
    {
      "type": "sign",
      "x": 34,
      "y": 19,
      "elevation": 0,
      "player_facing_dir": "BG_EVENT_PLAYER_FACING_ANY",
      "script": "UnionCity_AbandonedMuseum_AncientUnownTablet"
    },
    {
      "type": "sign",
      "x": 35,
      "y": 19,
      "elevation": 0,
      "player_facing_dir": "BG_EVENT_PLAYER_FACING_ANY",
      "script": "UnionCity_AbandonedMuseum_AncientUnownTablet"
    },
    {
      "type": "sign",
      "x": 34,
      "y": 17,
      "elevation": 0,
      "player_facing_dir": "BG_EVENT_PLAYER_FACING_ANY",
      "script": "UnionCity_AbandonedMuseum_HoOhRainbowFeather"
    },
    {
      "type": "sign",
      "x": 15,
      "y": 6,
      "elevation": 0,
      "player_facing_dir": "BG_EVENT_PLAYER_FACING_ANY",
      "script": "UnionCity_AbandonedMuseum_TheUnidentifiedPokemon"
    },
    {
      "type": "sign",
      "x": 25,
      "y": 6,
      "elevation": 0,
      "player_facing_dir": "BG_EVENT_PLAYER_FACING_ANY",
      "script": "UnionCity_AbandonedMuseum_ReconstructedAerodactylExhibit"
    }
  ]
}
